stack/__init__.py
stack/data.py
stack/test.txt
stack_package-0.1.0.dist-info/LICENSE
stack_package-0.1.0.dist-info/METADATA
stack_package-0.1.0.dist-info/WHEEL
stack_package-0.1.0.dist-info/top_level.txt
stack_package-0.1.0.dist-info/RECORD
